{
  "id": "klZlXN0ADArqDoIA0f8AISgXYiw",
  "name": "ORS Daily Discharge List Condensed for PDF",
  "description": "MOV0030 - v00.00.02 Last Modified: 09/11/2016 This report shows all scheduled movements out of a prison (court movements, confirmed releases, approved transfers, all approved temporary absences) for a date range specified at runtime. The data is grouped by date, movement type, destination name and surname in a printable format. (PDF) Please Note VIDEO CONFERENCING is not included in the listing.",
  "metadata": {
    "version": "1.0.0",
    "tags": ["MOV0030 v00.00.02 DPR"]
  },
  "datasource": [
    {
      "id": "nomis",
      "name": "NOMIS",
      "database": "DIGITAL_PRISON_REPORTING",
      "catalog": "nomis"
    }
  ],
  "dataset": [
    {
      "id": "3377299/DP3",
      "name": "Discharges",
      "description": "OR - Demographics",
      "datasource": "nomis",
      "query": "dataset_base_ AS (SELECT DISTINCT AT_OFFENDER.OFFENDER_ID_DISPLAY AS OFFENDER_ID_DISPLAY, AT_OFFENDER.LAST_NAME AS LAST_NAME, SUBSTR(AT_OFFENDER.FIRST_NAME, 1, 1) || '.' || CASE WHEN AT_OFFENDER.MIDDLE_NAME IS NULL THEN NULL ELSE SUBSTR(AT_OFFENDER.MIDDLE_NAME, 1, 1) || '.' || CASE WHEN AT_OFFENDER.MIDDLE_NAME_2 IS NULL THEN NULL ELSE SUBSTR(AT_OFFENDER.MIDDLE_NAME_2, 1, 1) || '.' END END AS INITIALS, SUBSTR(AT_AGENCY_INTERNAL_LOCATION_L4.DESCRIPTION, LENGTH(AT_AGENCY_INTERNAL_LOCATION_L4.AGY_LOC_ID) + 2, LENGTH(AT_AGENCY_INTERNAL_LOCATION_L4.DESCRIPTION)) AS UNIT_DESCRIPTION_4_SHORT, AT_IMPRISON_STATUSES.IMPRISONMENT_STATUS AS IMPRISONMENT_STATUS, CASE WHEN AT_OFFENDER_IND_SCHEDULES.EVENT_TYPE = 'ADM' THEN 'Admission' WHEN AT_OFFENDER_IND_SCHEDULES.EVENT_TYPE = 'ADMIN' THEN 'Administrative' WHEN AT_OFFENDER_IND_SCHEDULES.EVENT_TYPE = 'CRI' THEN 'Community Report In' WHEN AT_OFFENDER_IND_SCHEDULES.EVENT_TYPE = 'CRT' THEN 'Court' WHEN AT_OFFENDER_IND_SCHEDULES.EVENT_TYPE = 'INT' THEN 'Internal Transfer' WHEN AT_OFFENDER_IND_SCHEDULES.EVENT_TYPE = 'INTAKE' THEN 'Intake' WHEN AT_OFFENDER_IND_SCHEDULES.EVENT_TYPE = 'INTER' THEN 'Intermittent Custody' WHEN AT_OFFENDER_IND_SCHEDULES.EVENT_TYPE = 'OJ' THEN 'Outside Jurisdication' WHEN AT_OFFENDER_IND_SCHEDULES.EVENT_TYPE = 'REL' THEN 'Release' WHEN AT_OFFENDER_IND_SCHEDULES.EVENT_TYPE = 'TAP' THEN 'Temporary Absence/Home Leave' WHEN AT_OFFENDER_IND_SCHEDULES.EVENT_TYPE = 'TRN' THEN 'Transfers' ELSE AT_OFFENDER_IND_SCHEDULES.EVENT_TYPE END AS EVENT_TYPE_DESCRIPTION, AT_OFFENDER_IND_SCHEDULES.EVENT_DATE AS EVENT_DATE, TO_CHAR(AT_OFFENDER_IND_SCHEDULES.START_TIME, 'HH24:MI') AS FORMATTED_EVENT_START_TIME, ScheduledMovementReason.DESCRIPTION AS DESCRIPTION, CASE WHEN NOT AT_OFFENDER_IND_SCHEDULES.TO_AGY_LOC_ID IS NULL THEN AT_AGENCY_LOCATIONS_SCH_TO.DESCRIPTION WHEN AT_OFFENDER_IND_SCHEDULES.TO_AGY_LOC_ID IS NULL AND NOT AT_OFFENDER_IND_SCHEDULES.TO_ADDRESS_ID IS NULL AND DT_ROTL_ADDRESS_USAGE.ADDRESS_USAGE = 'ROTL' THEN CASE WHEN (ROTL_ADDRESSES.FLAT) IS NULL THEN NULL ELSE (ROTL_ADDRESSES.FLAT) END || ' ' || CASE WHEN (ROTL_ADDRESSES.PREMISE) IS NULL THEN NULL ELSE (ROTL_ADDRESSES.PREMISE) || ' ' END || CASE WHEN (ROTL_ADDRESSES.STREET) IS NULL THEN NULL ELSE (ROTL_ADDRESSES.STREET) || ' ' END WHEN AT_OFFENDER_IND_SCHEDULES.TO_AGY_LOC_ID IS NULL AND AT_OFFENDER_IND_SCHEDULES.TO_ADDRESS_ID IS NULL THEN 'No Location' ELSE AT_CORPORATES.CORPORATE_NAME END AS SCHEDULED_MOVEMENT_DESTINATION, AT_OFFENDER_ALERTS.ALERT_CODE AS ALERT_CODE, AT_OFFENDER_ALERTS.EXPIRY_DATE AS EXPIRY_DATE, AT_OFFENDER_ALERTS.ALERT_DATE AS ALERT_DATE, AT_OFFENDER_IND_SCHEDULES.EVENT_SUB_TYPE AS EVENT_SUB_TYPE, AT_OFFENDER_IND_SCHEDULES.EVENT_STATUS AS EVENT_STATUS, AT_OFFENDER_IND_SCHEDULES.ESCORT_CODE AS ESCORT_CODE, DT_PROPERTY_BOXES.SEAL_MARK AS SEAL_MARK, AT_OFFENDER_RELIGION.PROFILE_CODE AS PROFILE_CODE FROM ADDRESSES ROTL_ADDRESSES, OMS_OWNER.OFFENDERS AT_OFFENDER, OMS_OWNER.OFFENDER_IND_SCHEDULES AT_OFFENDER_IND_SCHEDULES, OMS_OWNER.AGENCY_INTERNAL_LOCATIONS AT_AGENCY_INTERNAL_LOCATION_L4, OMS_OWNER.REFERENCE_CODES ScheduledMovementReason, OMS_OWNER.OFFENDER_BOOKINGS AT_OFFENDER_BOOKING, OMS_OWNER.AGENCY_LOCATIONS AT_AGENCY_LOCATIONS_SCH_TO, OMS_OWNER.AGENCY_LOCATIONS AT_OFFENDERS_LOCATIONS, OMS_OWNER.AGENCY_LOCATIONS AT_AGENCY_LOCATIONS_SCH_FROM2, OMS_OWNER.AGENCY_LOCATIONS AT_WING_ESTABLISHMENT, OMS_OWNER.AGENCY_LOCATIONS AT_AGENCY_LOCATIONS_SCH_FROM, OMS_OWNER.OFFENDER_PROFILE_DETAILS AT_OFFENDER_RELIGION, OMS_OWNER.CASELOAD_AGENCY_LOCATIONS AT_CASELOAD_LOCATIONS, OMS_OWNER.IMPRISONMENT_STATUSES AT_IMPRISON_STATUSES, OMS_OWNER.OFFENDER_ALERTS AT_OFFENDER_ALERTS, USER_ACCESSIBLE_CASELOADS WING_CASELOAD_SECURITY, OMS_OWNER.CORPORATES AT_CORPORATES, (SELECT * FROM ADDRESS_USAGES WHERE ADDRESS_USAGE = 'ROTL') DT_ROTL_ADDRESS_USAGE, (SELECT Offender_Book_ID, Property_Container_ID, Active_Flag, Seal_Mark, Agy_Loc_ID, Expiry_Date, Internal_Location_ID, PROPOSED_DISPOSAL_DATE, Container_Code, Property_Only_Flag, Comment_Text FROM oms_owner.offender_ppty_containers WHERE active_flag = 'Y' AND Agy_Loc_ID = (SELECT ESTABLISHMENT_CODE FROM prompt_ /* = #Prompt('Establishment Code','A','Establishment\\Establishment Code',mono,free,,Not_Persistent,,User:3) */)) DT_PROPERTY_BOXES, OMS_OWNER.LIVING_UNITS AT_ALL_LIVING_UNITS, OMS_OWNER.OFFENDER_IMPRISON_STATUSES AT_OFFENDER_IMPRISON_STATUSES, V_CORPORATE_ADDRESSES AT_V_CORPORATE_ADDRESSES, ADDRESSES AT_CORPORATE_ADDRESSES WHERE (AT_OFFENDER.OFFENDER_ID = AT_OFFENDER_BOOKING.OFFENDER_ID) AND (AT_OFFENDER_ALERTS.OFFENDER_BOOK_ID (+) = AT_OFFENDER_BOOKING.OFFENDER_BOOK_ID) AND (AT_OFFENDER_BOOKING.LIVING_UNIT_ID = AT_AGENCY_INTERNAL_LOCATION_L4.INTERNAL_LOCATION_ID) AND (AT_OFFENDER_RELIGION.OFFENDER_BOOK_ID (+) = AT_OFFENDER_BOOKING.OFFENDER_BOOK_ID) AND (AT_OFFENDER_RELIGION.PROFILE_TYPE (+) = 'RELF') AND (AT_OFFENDER_BOOKING.OFFENDER_BOOK_ID = AT_OFFENDER_IND_SCHEDULES.OFFENDER_BOOK_ID) AND (AT_OFFENDER_IMPRISON_STATUSES.OFFENDER_BOOK_ID (+) = AT_OFFENDER_BOOKING.OFFENDER_BOOK_ID) AND (AT_OFFENDER_IMPRISON_STATUSES.LATEST_STATUS = 'Y' OR AT_OFFENDER_IMPRISON_STATUSES.LATEST_STATUS IS NULL) AND (AT_OFFENDERS_LOCATIONS.AGENCY_LOCATION_TYPE = 'INST') AND (AT_OFFENDER_IND_SCHEDULES.EVENT_SUB_TYPE = ScheduledMovementReason.CODE) AND (ScheduledMovementReason.DOMAIN = 'MOVE_RSN') AND (AT_OFFENDER_IND_SCHEDULES.TO_AGY_LOC_ID = AT_AGENCY_LOCATIONS_SCH_TO.AGY_LOC_ID (+)) AND (AT_OFFENDER_IND_SCHEDULES.AGY_LOC_ID = AT_AGENCY_LOCATIONS_SCH_FROM.AGY_LOC_ID (+)) AND (AT_AGENCY_LOCATIONS_SCH_FROM2.AGENCY_LOCATION_TYPE = 'INST') AND (AT_CORPORATE_ADDRESSES.ADDRESS_ID = AT_V_CORPORATE_ADDRESSES.ADDRESS_ID (+)) AND (AT_V_CORPORATE_ADDRESSES.CORPORATE_ID = AT_CORPORATES.CORPORATE_ID (+)) AND (AT_OFFENDER_IND_SCHEDULES.TO_ADDRESS_ID = AT_CORPORATE_ADDRESSES.ADDRESS_ID (+)) AND (AT_OFFENDER_IND_SCHEDULES.TO_ADDRESS_ID = ROTL_ADDRESSES.ADDRESS_ID (+)) AND (AT_OFFENDER_IND_SCHEDULES.TO_ADDRESS_ID = DT_ROTL_ADDRESS_USAGE.ADDRESS_ID (+)) AND (AT_AGENCY_LOCATIONS_SCH_FROM.AGY_LOC_ID = AT_AGENCY_LOCATIONS_SCH_FROM2.AGY_LOC_ID) AND (AT_OFFENDER_BOOKING.LIVING_UNIT_ID (+) = AT_ALL_LIVING_UNITS.LIVING_UNIT_ID) AND (AT_CASELOAD_LOCATIONS.AGY_LOC_ID = AT_OFFENDER_BOOKING.AGY_LOC_ID) AND (AT_CASELOAD_LOCATIONS.AGY_LOC_ID = AT_OFFENDERS_LOCATIONS.AGY_LOC_ID (+)) AND (NOT AT_CASELOAD_LOCATIONS.AGY_LOC_ID IN ('OUT', 'TRN') AND NOT AT_CASELOAD_LOCATIONS.CASELOAD_ID IN ('ADMINC', 'CADM_I', 'MULTI')) AND (AT_AGENCY_INTERNAL_LOCATION_L4.AGY_LOC_ID = AT_WING_ESTABLISHMENT.AGY_LOC_ID) AND (AT_WING_ESTABLISHMENT.AGY_LOC_ID = WING_CASELOAD_SECURITY.CASELOAD_ID) AND (AT_IMPRISON_STATUSES.IMPRISONMENT_STATUS (+) = AT_OFFENDER_IMPRISON_STATUSES.IMPRISONMENT_STATUS) AND (AT_OFFENDER_BOOKING.OFFENDER_BOOK_ID = DT_PROPERTY_BOXES.OFFENDER_BOOK_ID (+)) AND (WING_CASELOAD_SECURITY.USERNAME = UPPER((SELECT username FROM context_ /* = #Variable('BOUSER') */))) AND ((AT_OFFENDERS_LOCATIONS.AGY_LOC_ID = (SELECT ESTABLISHMENT_CODE FROM prompt_ /* = #Prompt('Establishment Code','A','Establishment\\Establishment Code',mono,free,,Not_Persistent,,User:3) */)) AND (AT_ALL_LIVING_UNITS.AGY_LOC_ID || '-' || AT_ALL_LIVING_UNITS.LEVEL_1_CODE IN (SELECT WING FROM prompt_ /* = #Prompt('Wing (All for all)','A','Cell\\Location LOV',multi,free,,Not_Persistent,,User:4) */) OR 'All' IN (SELECT WING FROM prompt_ /* = #Prompt('Wing (All for all)','A','Cell\\Location LOV',multi,free,,Not_Persistent,,User:4) */)) AND (AT_OFFENDER_BOOKING.ACTIVE_FLAG = 'Y') AND (AT_AGENCY_LOCATIONS_SCH_FROM2.AGENCY_LOCATION_TYPE = 'INST' AND AT_AGENCY_LOCATIONS_SCH_FROM2.AGY_LOC_ID = (SELECT ESTABLISHMENT_CODE FROM prompt_ /* = #Prompt('Establishment Code','A','Scheduled TAPS, Transfers and Appointments\\Scheduled Departure Establishment Code',mono,free,,Not_Persistent,,User:2) */)) AND AT_OFFENDER_IND_SCHEDULES.EVENT_DATE >= (SELECT SCHEDULE_DATE FROM prompt_ /* = #prompt('Schedule Date Start','D',,Mono,Free,Not_Persistent,,User:0) */) AND AT_OFFENDER_IND_SCHEDULES.EVENT_DATE <= (SELECT SCHEDULE_DATE FROM prompt_ /* = #prompt('Schedule Date End','D',,Mono,Free,Not_Persistent,,User:1) */) AND AT_OFFENDER_IND_SCHEDULES.EVENT_DATE >= TRUNC(CURRENT_TIMESTAMP) AND AT_OFFENDER_IND_SCHEDULES.DIRECTION_CODE = 'OUT' AND AT_OFFENDER_IND_SCHEDULES.EVENT_TYPE IN ('TAP', 'TRN') AND NOT ScheduledMovementReason.DESCRIPTION IN ('Video Link (Court Appearance)', 'Video Link Appeal', 'Video Link Bail Applicaton', 'Video Link Breach Hearing', 'Video Link Civil Hearing', 'Video Link Committal Hearing', 'Video Link Court Review', 'Video Link Expedited Breach Hearing', 'Video Link Newton Hearing', 'Video Link Plea and Direction Hearing', 'Video Link Police Production', 'Video Link Proceeds of Crime Hearing', 'Video Link Production (Sentencing)', 'Video Link Production (Unsent.)', 'Video Link Remittal Hearing', 'Video Link Witness Production') AND AT_OFFENDER_IND_SCHEDULES.EVENT_CLASS = 'EXT_MOV' AND AT_OFFENDER_IND_SCHEDULES.EVENT_STATUS = 'SCH') UNION SELECT DISTINCT AT_OFFENDER.OFFENDER_ID_DISPLAY AS OFFENDER_ID_DISPLAY, AT_OFFENDER.LAST_NAME AS LAST_NAME, SUBSTR(AT_OFFENDER.FIRST_NAME, 1, 1) || '.' || CASE WHEN AT_OFFENDER.MIDDLE_NAME IS NULL THEN NULL ELSE SUBSTR(AT_OFFENDER.MIDDLE_NAME, 1, 1) || '.' || CASE WHEN AT_OFFENDER.MIDDLE_NAME_2 IS NULL THEN NULL ELSE SUBSTR(AT_OFFENDER.MIDDLE_NAME_2, 1, 1) || '.' END END AS INITIALS, SUBSTR(AT_AGENCY_INTERNAL_LOCATION_L4.DESCRIPTION, LENGTH(AT_AGENCY_INTERNAL_LOCATION_L4.AGY_LOC_ID) + 2, LENGTH(AT_AGENCY_INTERNAL_LOCATION_L4.DESCRIPTION)) AS UNIT_DESCRIPTION_4_SHORT, AT_IMPRISON_STATUSES.IMPRISONMENT_STATUS AS IMPRISONMENT_STATUS, 'Release' AS EVENT_TYPE_DESCRIPTION, AT_OFFENDER_RELEASE_DETAILS.RELEASE_DATE AS EVENT_DATE, '' AS FORMATTED_EVENT_START_TIME, AT_RELEASE_REASON.DESCRIPTION AS DESCRIPTION, '- ' AS SCHEDULED_MOVEMENT_DESTINATION, AT_OFFENDER_ALERTS.ALERT_CODE AS ALERT_CODE, AT_OFFENDER_ALERTS.EXPIRY_DATE AS EXPIRY_DATE, AT_OFFENDER_ALERTS.ALERT_DATE AS ALERT_DATE, 'Release' AS EVENT_SUB_TYPE, AT_OFFENDER_RELEASE_DETAILS.EVENT_STATUS AS EVENT_STATUS, '' AS ESCORT_CODE, DT_PROPERTY_BOXES.SEAL_MARK AS SEAL_MARK, AT_OFFENDER_RELIGION.PROFILE_CODE AS PROFILE_CODE FROM OMS_OWNER.OFFENDERS AT_OFFENDER, OMS_OWNER.AGENCY_INTERNAL_LOCATIONS AT_AGENCY_INTERNAL_LOCATION_L4, OMS_OWNER.REFERENCE_CODES AT_RELEASE_REASON, OMS_OWNER.OFFENDER_SENT_CALCULATIONS AT_OFFENDER_SENT_CALCULATIONS, OMS_OWNER.OFFENDER_BOOKINGS AT_OFFENDER_BOOKING, OMS_OWNER.AGENCY_LOCATIONS AT_OFFENDERS_LOCATIONS, OMS_OWNER.AGENCY_LOCATIONS AT_WING_ESTABLISHMENT, OMS_OWNER.OFFENDER_PROFILE_DETAILS AT_OFFENDER_RELIGION, OMS_OWNER.CASELOAD_AGENCY_LOCATIONS AT_CASELOAD_LOCATIONS, OMS_OWNER.IMPRISONMENT_STATUSES AT_IMPRISON_STATUSES, OMS_OWNER.OFFENDER_ALERTS AT_OFFENDER_ALERTS, USER_ACCESSIBLE_CASELOADS WING_CASELOAD_SECURITY, OMS_OWNER.OFFENDER_RELEASE_DETAILS AT_OFFENDER_RELEASE_DETAILS, (SELECT Offender_Book_ID, Property_Container_ID, Active_Flag, Seal_Mark, Agy_Loc_ID, Expiry_Date, Internal_Location_ID, PROPOSED_DISPOSAL_DATE, Container_Code, Property_Only_Flag, Comment_Text FROM oms_owner.offender_ppty_containers WHERE active_flag = 'Y' AND Agy_Loc_ID = (SELECT ESTABLISHMENT_CODE FROM prompt_ /* = #Prompt('Establishment Code','A','Establishment\\Establishment Code',mono,free,,Not_Persistent,,User:3) */)) DT_PROPERTY_BOXES, OMS_OWNER.LIVING_UNITS AT_ALL_LIVING_UNITS, OMS_OWNER.OFFENDER_IMPRISON_STATUSES AT_OFFENDER_IMPRISON_STATUSES WHERE (AT_OFFENDER.OFFENDER_ID = AT_OFFENDER_BOOKING.OFFENDER_ID) AND (AT_OFFENDER_ALERTS.OFFENDER_BOOK_ID (+) = AT_OFFENDER_BOOKING.OFFENDER_BOOK_ID) AND (AT_OFFENDER_BOOKING.LIVING_UNIT_ID = AT_AGENCY_INTERNAL_LOCATION_L4.INTERNAL_LOCATION_ID) AND (AT_OFFENDER_RELIGION.OFFENDER_BOOK_ID (+) = AT_OFFENDER_BOOKING.OFFENDER_BOOK_ID) AND (AT_OFFENDER_RELIGION.PROFILE_TYPE (+) = 'RELF') AND (AT_OFFENDER_BOOKING.OFFENDER_BOOK_ID = AT_OFFENDER_SENT_CALCULATIONS.OFFENDER_BOOK_ID (+)) AND (AT_OFFENDER_IMPRISON_STATUSES.OFFENDER_BOOK_ID (+) = AT_OFFENDER_BOOKING.OFFENDER_BOOK_ID) AND (AT_OFFENDER_IMPRISON_STATUSES.LATEST_STATUS = 'Y' OR AT_OFFENDER_IMPRISON_STATUSES.LATEST_STATUS IS NULL) AND (AT_OFFENDERS_LOCATIONS.AGENCY_LOCATION_TYPE = 'INST') AND (AT_OFFENDER_BOOKING.OFFENDER_BOOK_ID = AT_OFFENDER_RELEASE_DETAILS.OFFENDER_BOOK_ID (+)) AND (AT_OFFENDER_RELEASE_DETAILS.MOVEMENT_REASON_CODE = AT_RELEASE_REASON.CODE (+)) AND (AT_RELEASE_REASON.DOMAIN (+) = 'MOVE_RSN') AND (AT_RELEASE_REASON.PARENT_CODE (+) = 'REL') AND (AT_OFFENDER_BOOKING.LIVING_UNIT_ID (+) = AT_ALL_LIVING_UNITS.LIVING_UNIT_ID) AND (AT_CASELOAD_LOCATIONS.AGY_LOC_ID = AT_OFFENDER_BOOKING.AGY_LOC_ID) AND (AT_CASELOAD_LOCATIONS.AGY_LOC_ID = AT_OFFENDERS_LOCATIONS.AGY_LOC_ID (+)) AND (NOT AT_CASELOAD_LOCATIONS.AGY_LOC_ID IN ('OUT', 'TRN') AND NOT AT_CASELOAD_LOCATIONS.CASELOAD_ID IN ('ADMINC', 'CADM_I', 'MULTI')) AND (AT_AGENCY_INTERNAL_LOCATION_L4.AGY_LOC_ID = AT_WING_ESTABLISHMENT.AGY_LOC_ID) AND (AT_WING_ESTABLISHMENT.AGY_LOC_ID = WING_CASELOAD_SECURITY.CASELOAD_ID) AND (AT_IMPRISON_STATUSES.IMPRISONMENT_STATUS (+) = AT_OFFENDER_IMPRISON_STATUSES.IMPRISONMENT_STATUS) AND (AT_OFFENDER_BOOKING.OFFENDER_BOOK_ID = DT_PROPERTY_BOXES.OFFENDER_BOOK_ID (+)) AND (WING_CASELOAD_SECURITY.USERNAME = UPPER((SELECT username FROM context_ /* = #Variable('BOUSER') */))) AND ((AT_OFFENDERS_LOCATIONS.AGY_LOC_ID = (SELECT ESTABLISHMENT_CODE FROM prompt_ /* = #Prompt('Establishment Code','A','Establishment\\Establishment Code',mono,free,,Not_Persistent,,User:3) */)) AND (AT_ALL_LIVING_UNITS.AGY_LOC_ID || '-' || AT_ALL_LIVING_UNITS.LEVEL_1_CODE IN (SELECT WING FROM prompt_ /* = #Prompt('Wing (All for all)','A','Cell\\Location LOV',multi,free,,Not_Persistent,,User:4) */) OR 'All' IN (SELECT WING FROM prompt_ /* = #Prompt('Wing (All for all)','A','Cell\\Location LOV',multi,free,,Not_Persistent,,User:4) */)) AND (AT_OFFENDER_BOOKING.ACTIVE_FLAG = 'Y') AND (AT_OFFENDER_SENT_CALCULATIONS.OFFENDER_SENT_CALCULATION_ID = (SELECT MAX(A.OFFENDER_SENT_CALCULATION_ID) FROM OMS_OWNER.OFFENDER_SENT_CALCULATIONS A WHERE AT_OFFENDER_SENT_CALCULATIONS.OFFENDER_BOOK_ID = A.OFFENDER_BOOK_ID) OR AT_OFFENDER_SENT_CALCULATIONS.OFFENDER_BOOK_ID IS NULL /* END Filter: Hierarchies/Sentence/Sentence Dates/Other Sentence Dates/''Latest Calculation Date'' */) /* START Filter: Hierarchies/Sentence/Sentence Dates/Other Sentence Dates/''Latest Calculation Date'' */ AND AT_OFFENDER_RELEASE_DETAILS.RELEASE_DATE >= (SELECT SCHEDULE_DATE FROM prompt_ /* = #prompt('Schedule Date Start','D',,Mono,Free,Not_Persistent,,User:0) */) AND AT_OFFENDER_RELEASE_DETAILS.RELEASE_DATE <= (SELECT SCHEDULE_DATE FROM prompt_ /* = #prompt('Schedule Date End','D',,Mono,Free,Not_Persistent,,User:1) */) AND AT_OFFENDER_RELEASE_DETAILS.RELEASE_DATE >= TRUNC(CURRENT_TIMESTAMP) AND AT_OFFENDER_RELEASE_DETAILS.EVENT_STATUS IN ('SCH')) UNION SELECT DISTINCT AT_OFFENDER.OFFENDER_ID_DISPLAY AS OFFENDER_ID_DISPLAY, AT_OFFENDER.LAST_NAME AS LAST_NAME, SUBSTR(AT_OFFENDER.FIRST_NAME, 1, 1) || '.' || CASE WHEN AT_OFFENDER.MIDDLE_NAME IS NULL THEN NULL ELSE SUBSTR(AT_OFFENDER.MIDDLE_NAME, 1, 1) || '.' || CASE WHEN AT_OFFENDER.MIDDLE_NAME_2 IS NULL THEN NULL ELSE SUBSTR(AT_OFFENDER.MIDDLE_NAME_2, 1, 1) || '.' END END AS INITIALS, SUBSTR(AT_AGENCY_INTERNAL_LOCATION_L4.DESCRIPTION, LENGTH(AT_AGENCY_INTERNAL_LOCATION_L4.AGY_LOC_ID) + 2, LENGTH(AT_AGENCY_INTERNAL_LOCATION_L4.DESCRIPTION)) AS UNIT_DESCRIPTION_4_SHORT, AT_IMPRISON_STATUSES.IMPRISONMENT_STATUS AS IMPRISONMENT_STATUS, 'Court Event' AS EVENT_TYPE_DESCRIPTION, AT_COURT_EVENT_MVMTS.EVENT_DATE AS EVENT_DATE, TO_CHAR(AT_COURT_EVENT_MVMTS.START_TIME, 'HH24:MI') AS FORMATTED_EVENT_START_TIME, CourtMovementReason.DESCRIPTION AS DESCRIPTION, AT_DESTINATION_COURT.DESCRIPTION AS SCHEDULED_MOVEMENT_DESTINATION, AT_OFFENDER_ALERTS.ALERT_CODE AS ALERT_CODE, AT_OFFENDER_ALERTS.EXPIRY_DATE AS EXPIRY_DATE, AT_OFFENDER_ALERTS.ALERT_DATE AS ALERT_DATE, 'Court' AS EVENT_SUB_TYPE, AT_COURT_EVENT_MVMTS.EVENT_STATUS AS EVENT_STATUS, '' AS ESCORT_CODE, DT_PROPERTY_BOXES.SEAL_MARK AS SEAL_MARK, AT_OFFENDER_RELIGION.PROFILE_CODE AS PROFILE_CODE FROM OMS_OWNER.OFFENDERS AT_OFFENDER, OMS_OWNER.AGENCY_INTERNAL_LOCATIONS AT_AGENCY_INTERNAL_LOCATION_L4, OMS_OWNER.REFERENCE_CODES CourtMovementReason, OMS_OWNER.OFFENDER_BOOKINGS AT_OFFENDER_BOOKING, OMS_OWNER.AGENCY_LOCATIONS AT_DESTINATION_COURT, OMS_OWNER.AGENCY_LOCATIONS AT_OFFENDERS_LOCATIONS, OMS_OWNER.AGENCY_LOCATIONS AT_WING_ESTABLISHMENT, OMS_OWNER.OFFENDER_PROFILE_DETAILS AT_OFFENDER_RELIGION, OMS_OWNER.CASELOAD_AGENCY_LOCATIONS AT_CASELOAD_LOCATIONS, OMS_OWNER.IMPRISONMENT_STATUSES AT_IMPRISON_STATUSES, OMS_OWNER.OFFENDER_ALERTS AT_OFFENDER_ALERTS, USER_ACCESSIBLE_CASELOADS WING_CASELOAD_SECURITY, OMS_OWNER.COURT_EVENTS AT_COURT_EVENT_MVMTS, (SELECT Offender_Book_ID, Property_Container_ID, Active_Flag, Seal_Mark, Agy_Loc_ID, Expiry_Date, Internal_Location_ID, PROPOSED_DISPOSAL_DATE, Container_Code, Property_Only_Flag, Comment_Text FROM oms_owner.offender_ppty_containers WHERE active_flag = 'Y' AND Agy_Loc_ID = (SELECT ESTABLISHMENT_CODE FROM prompt_ /* = #Prompt('Establishment Code','A','Establishment\\Establishment Code',mono,free,,Not_Persistent,,User:3) */)) DT_PROPERTY_BOXES, OMS_OWNER.LIVING_UNITS AT_ALL_LIVING_UNITS, OMS_OWNER.OFFENDER_IMPRISON_STATUSES AT_OFFENDER_IMPRISON_STATUSES WHERE (AT_OFFENDER.OFFENDER_ID = AT_OFFENDER_BOOKING.OFFENDER_ID) AND (AT_OFFENDER_ALERTS.OFFENDER_BOOK_ID (+) = AT_OFFENDER_BOOKING.OFFENDER_BOOK_ID) AND (AT_OFFENDER_BOOKING.LIVING_UNIT_ID = AT_AGENCY_INTERNAL_LOCATION_L4.INTERNAL_LOCATION_ID) AND (AT_OFFENDER_RELIGION.OFFENDER_BOOK_ID (+) = AT_OFFENDER_BOOKING.OFFENDER_BOOK_ID) AND (AT_OFFENDER_RELIGION.PROFILE_TYPE (+) = 'RELF') AND (AT_OFFENDER_IMPRISON_STATUSES.OFFENDER_BOOK_ID (+) = AT_OFFENDER_BOOKING.OFFENDER_BOOK_ID) AND (AT_OFFENDER_IMPRISON_STATUSES.LATEST_STATUS = 'Y' OR AT_OFFENDER_IMPRISON_STATUSES.LATEST_STATUS IS NULL) AND (AT_OFFENDERS_LOCATIONS.AGENCY_LOCATION_TYPE = 'INST') AND (CourtMovementReason.PARENT_CODE = 'CRT') AND (CourtMovementReason.DOMAIN = 'MOVE_RSN') AND (AT_OFFENDER_BOOKING.OFFENDER_BOOK_ID = AT_COURT_EVENT_MVMTS.OFFENDER_BOOK_ID) AND (AT_COURT_EVENT_MVMTS.COURT_EVENT_TYPE = CourtMovementReason.CODE) AND (AT_COURT_EVENT_MVMTS.AGY_LOC_ID = AT_DESTINATION_COURT.AGY_LOC_ID) AND (AT_OFFENDER_BOOKING.LIVING_UNIT_ID (+) = AT_ALL_LIVING_UNITS.LIVING_UNIT_ID) AND (AT_CASELOAD_LOCATIONS.AGY_LOC_ID = AT_OFFENDER_BOOKING.AGY_LOC_ID) AND (AT_CASELOAD_LOCATIONS.AGY_LOC_ID = AT_OFFENDERS_LOCATIONS.AGY_LOC_ID (+)) AND (NOT AT_CASELOAD_LOCATIONS.AGY_LOC_ID IN ('OUT', 'TRN') AND NOT AT_CASELOAD_LOCATIONS.CASELOAD_ID IN ('ADMINC', 'CADM_I', 'MULTI')) AND (AT_AGENCY_INTERNAL_LOCATION_L4.AGY_LOC_ID = AT_WING_ESTABLISHMENT.AGY_LOC_ID) AND (AT_WING_ESTABLISHMENT.AGY_LOC_ID = WING_CASELOAD_SECURITY.CASELOAD_ID) AND (AT_IMPRISON_STATUSES.IMPRISONMENT_STATUS (+) = AT_OFFENDER_IMPRISON_STATUSES.IMPRISONMENT_STATUS) AND (AT_OFFENDER_BOOKING.OFFENDER_BOOK_ID = DT_PROPERTY_BOXES.OFFENDER_BOOK_ID (+)) AND (WING_CASELOAD_SECURITY.USERNAME = UPPER((SELECT username FROM context_ /* = #Variable('BOUSER') */))) AND ((AT_OFFENDERS_LOCATIONS.AGY_LOC_ID = (SELECT ESTABLISHMENT_CODE FROM prompt_ /* = #Prompt('Establishment Code','A','Establishment\\Establishment Code',mono,free,,Not_Persistent,,User:3) */)) AND (AT_ALL_LIVING_UNITS.AGY_LOC_ID || '-' || AT_ALL_LIVING_UNITS.LEVEL_1_CODE IN (SELECT WING FROM prompt_ /* = #Prompt('Wing (All for all)','A','Cell\\Location LOV',multi,free,,Not_Persistent,,User:4) */) OR 'All' IN (SELECT WING FROM prompt_ /* = #Prompt('Wing (All for all)','A','Cell\\Location LOV',multi,free,,Not_Persistent,,User:4) */)) AND (AT_OFFENDER_BOOKING.ACTIVE_FLAG = 'Y') AND AT_COURT_EVENT_MVMTS.EVENT_DATE >= (SELECT SCHEDULE_DATE FROM prompt_ /* = #prompt('Schedule Date Start','D',,Mono,Free,Not_Persistent,,User:0) */) AND AT_COURT_EVENT_MVMTS.EVENT_DATE <= (SELECT SCHEDULE_DATE FROM prompt_ /* = #prompt('Schedule Date End','D',,Mono,Free,Not_Persistent,,User:1) */) AND AT_COURT_EVENT_MVMTS.EVENT_DATE >= TRUNC(CURRENT_TIMESTAMP) AND AT_COURT_EVENT_MVMTS.EVENT_STATUS = 'SCH' AND AT_COURT_EVENT_MVMTS.DIRECTION_CODE = 'OUT' AND NOT CourtMovementReason.DESCRIPTION IN ('Video Link (Court Appearance)', 'Video Link Appeal', 'Video Link Bail Applicaton', 'Video Link Breach Hearing', 'Video Link Civil Hearing', 'Video Link Committal Hearing', 'Video Link Court Review', 'Video Link Expedited Breach Hearing', 'Video Link Newton Hearing', 'Video Link Plea and Direction Hearing', 'Video Link Police Production', 'Video Link Proceeds of Crime Hearing', 'Video Link Production (Sentencing)', 'Video Link Production (Unsent.)', 'Video Link Remittal Hearing', 'Video Link Witness Production'))), dataset_ AS (SELECT OFFENDER_ID_DISPLAY, LAST_NAME, INITIALS, UNIT_DESCRIPTION_4_SHORT, IMPRISONMENT_STATUS, EVENT_TYPE_DESCRIPTION, EVENT_DATE, FORMATTED_EVENT_START_TIME, DESCRIPTION, SCHEDULED_MOVEMENT_DESTINATION, ALERT_CODE, EXPIRY_DATE, ALERT_DATE, EVENT_SUB_TYPE, EVENT_STATUS, ESCORT_CODE, SEAL_MARK, PROFILE_CODE, CASE WHEN LEFT(SCHEDULED_MOVEMENT_REASON, 10) = 'Video Link' THEN 'Court Event - Video Link' ELSE EVENT_TYPE_DESCRIPTION END AS V_MOVEMENT_TYPE, CASE WHEN SCHEDULED_MOVEMENT_DESTINATION IS NULL THEN '-' ELSE SCHEDULED_MOVEMENT_DESTINATION END AS V_DESTINATION FROM dataset_base_)",
      "parameters": [
        {
          "index": 0,
          "name": "establishment_code",
          "filterType": "text",
          "reportFieldType": "string",
          "display": "Establishment Code",
          "description": "@Prompt('Establishment Code','A','Establishment\\Establishment Code',mono,free,,Not_Persistent,,User:3)",
          "mandatory": "true"
        },
        {
          "index": 1,
          "name": "wing",
          "filterType": "text",
          "reportFieldType": "string",
          "display": "Wing (All for all)",
          "description": "@Prompt('Wing (All for all)','A','Cell\\Location LOV',multi,free,,Not_Persistent,,User:4)",
          "mandatory": "true"
        },
        {
          "index": 2,
          "name": "schedule_date",
          "filterType": "text",
          "reportFieldType": "date",
          "display": "Schedule Date Start",
          "description": "@prompt('Schedule Date Start','D',,Mono,Free,Not_Persistent,,User:0)",
          "mandatory": "true"
        }
      ],
      "schema": {
        "field": [
          {
            "index": 0,
            "name": "OFFENDER_ID_DISPLAY",
            "type": "string",
            "display": "NOMS Number",
            "legacyId": "DP3.DO44",
            "legacySqlClass": "column"
          },
          {
            "index": 1,
            "name": "LAST_NAME",
            "type": "string",
            "display": "Last Name",
            "legacyId": "DP3.DO45",
            "legacySqlClass": "column"
          },
          {
            "index": 2,
            "name": "INITIALS",
            "type": "string",
            "display": "Initials",
            "legacyId": "DP3.DO71",
            "legacySqlClass": "column"
          },
          {
            "index": 3,
            "name": "UNIT_DESCRIPTION_4_SHORT",
            "type": "string",
            "display": "Unit Description 4 Short",
            "legacyId": "DP3.DO427",
            "legacySqlClass": "column"
          },
          {
            "index": 4,
            "name": "IMPRISONMENT_STATUS",
            "type": "string",
            "display": "Main Legal Status",
            "legacyId": "DP3.DO3c7",
            "legacySqlClass": "column"
          },
          {
            "index": 5,
            "name": "EVENT_TYPE_DESCRIPTION",
            "type": "string",
            "display": "Event Type Description",
            "legacyId": "DP3.DO8c7",
            "legacySqlClass": "column"
          },
          {
            "index": 6,
            "name": "EVENT_DATE",
            "type": "date",
            "display": "Event Date",
            "legacyId": "DP3.DO83e",
            "legacySqlClass": "column"
          },
          {
            "index": 7,
            "name": "FORMATTED_EVENT_START_TIME",
            "type": "string",
            "display": "Formatted Event Start Time",
            "legacyId": "DP3.DO1063",
            "legacySqlClass": "column"
          },
          {
            "index": 8,
            "name": "DESCRIPTION",
            "type": "string",
            "display": "Scheduled Movement Reason",
            "legacyId": "DP3.DO892",
            "legacySqlClass": "column"
          },
          {
            "index": 9,
            "name": "SCHEDULED_MOVEMENT_DESTINATION",
            "type": "string",
            "display": "Scheduled Movement Destination",
            "legacyId": "DP3.DO8f4",
            "legacySqlClass": "column"
          },
          {
            "index": 10,
            "name": "ALERT_CODE",
            "type": "string",
            "display": "Alert Type Code",
            "legacyId": "DP3.DO7e",
            "legacySqlClass": "column"
          },
          {
            "index": 11,
            "name": "EXPIRY_DATE",
            "type": "date",
            "display": "Expiry Date",
            "legacyId": "DP3.DO82",
            "legacySqlClass": "column"
          },
          {
            "index": 12,
            "name": "ALERT_DATE",
            "type": "date",
            "display": "Alert Effective Date",
            "legacyId": "DP3.DO59e",
            "legacySqlClass": "column"
          },
          {
            "index": 13,
            "name": "EVENT_SUB_TYPE",
            "type": "string",
            "display": "Event Sub Type Code",
            "legacyId": "DP3.DO87a",
            "legacySqlClass": "column"
          },
          {
            "index": 14,
            "name": "EVENT_STATUS",
            "type": "string",
            "display": "Event Status",
            "legacyId": "DP3.DO842",
            "legacySqlClass": "column"
          },
          {
            "index": 15,
            "name": "ESCORT_CODE",
            "type": "string",
            "display": "Escort Code",
            "legacyId": "DP3.DOc93",
            "legacySqlClass": "column"
          },
          {
            "index": 16,
            "name": "SEAL_MARK",
            "type": "string",
            "display": "Seal Mark",
            "legacyId": "DP3.DOc3c",
            "legacySqlClass": "column"
          },
          {
            "index": 17,
            "name": "PROFILE_CODE",
            "type": "string",
            "display": "Religion",
            "legacyId": "DP3.DOb0",
            "legacySqlClass": "column"
          },
          {
            "index": 18,
            "name": "V_MOVEMENT_TYPE",
            "type": "string",
            "display": "V_MOVEMENT_TYPE",
            "legacyId": "???",
            "legacySqlClass": "alias"
          },
          {
            "index": 19,
            "name": "V_DESTINATION",
            "type": "string",
            "display": "V_DESTINATION",
            "legacyId": "???",
            "legacySqlClass": "alias"
          }
        ]
      }
    }
  ],
  "policy": [
    {
      "id": "access",
      "type": "access",
      "rule": [
        {
          "effect": "permit",
          "condition": [
            {
              "match": ["${role}", "ROLE_PRISONS_REPORTING_USER"]
            }
          ]
        }
      ]
    }
  ],
  "report": [
    {
      "id": "157660.RS",
      "name": "Daily Discharge List by Surname",
      "classification": "OFFICIAL",
      "version": "1.0.0",
      "render": "HTML",
      "dataset": "3377299/DP3",
      "specification": {
        "template": "list-section",
        "field": [
          {
            "name": "$ref:OFFENDER_ID_DISPLAY",
            "display": "NOMS Number",
            "formula": "",
            "visible": "true",
            "sortable": true,
            "defaultsort": false
          },
          {
            "name": "$ref:LAST_NAME",
            "display": "Last Name",
            "formula": "",
            "visible": "true",
            "sortable": true,
            "defaultsort": false
          },
          {
            "name": "$ref:INITIALS",
            "display": "Initials",
            "formula": "",
            "visible": "true",
            "sortable": true,
            "defaultsort": false
          },
          {
            "name": "$ref:PROFILE_CODE",
            "display": "Religion",
            "formula": "",
            "visible": "true",
            "sortable": true,
            "defaultsort": false
          },
          {
            "name": "$ref:v_Movement_Type",
            "display": "",
            "formula": "=If(Left([Scheduled Movement Reason];10)=\"Video Link\";\"Court Event - Video Link\";[Event Type Description])",
            "visible": "true",
            "sortable": true,
            "defaultsort": false
          },
          {
            "name": "$ref:UNIT_DESCRIPTION_4_SHORT",
            "display": "Unit Description 4 Short",
            "formula": "",
            "visible": "true",
            "sortable": true,
            "defaultsort": false
          },
          {
            "name": "$ref:DESCRIPTION",
            "display": "Scheduled Movement Reason",
            "formula": "",
            "visible": "true",
            "sortable": true,
            "defaultsort": false
          },
          {
            "name": "$ref:v_Destination",
            "display": "",
            "formula": "=If(IsNull([Scheduled Movement Destination]);\"-\";[Scheduled Movement Destination])",
            "visible": "true",
            "sortable": true,
            "defaultsort": false
          },
          {
            "name": "$ref:v_NFR_marker",
            "display": "",
            "formula": "=If(Max(If([Alert Type Code]=\"XNR\" And [Expiry Date]>=[Event Date] Or [Alert Type Code]=\"XNR\" And IsNull([Expiry Date]);1;0))=1;\"X\";\"\")",
            "visible": "true",
            "sortable": true,
            "defaultsort": false
          }
        ]
      }
    }
  ]
}
